Adafruit_SHT31.py
Adafruit_SHT31_Example.py
LICENSE
MANIFEST.in
README.md
setup.py
Adafruit_SHT31.egg-info/PKG-INFO
Adafruit_SHT31.egg-info/SOURCES.txt
Adafruit_SHT31.egg-info/dependency_links.txt
Adafruit_SHT31.egg-info/top_level.txt