Metadata-Version: 1.1
Name: Adafruit-SHT31
Version: 1.0.2
Summary: Python Library for Adafruit SHT31 module
Home-page: https://github.com/ralf1070/Adafruit_Python_SHT31
Author: UNKNOWN
Author-email: UNKNOWN
License: MIT
Keywords: SHT31
Platform: UNKNOWN
Classifier: Development Status :: 3 - Alpha
Classifier: Intended Audience :: Developers
Classifier: License :: OSI Approved :: MIT License
Classifier: Programming Language :: Python :: 2
